padatious/__init__.py
padatious/__main__.py
padatious/bracket_expansion.py
padatious/entity.py
padatious/entity_edge.py
padatious/entity_manager.py
padatious/id_manager.py
padatious/intent.py
padatious/intent_container.py
padatious/intent_manager.py
padatious/match_data.py
padatious/pos_intent.py
padatious/simple_intent.py
padatious/train_data.py
padatious/trainable.py
padatious/training_manager.py
padatious/util.py
padatious_phoenix-0.4.9.0.dist-info/LICENSE
padatious_phoenix-0.4.9.0.dist-info/METADATA
padatious_phoenix-0.4.9.0.dist-info/WHEEL
padatious_phoenix-0.4.9.0.dist-info/entry_points.txt
padatious_phoenix-0.4.9.0.dist-info/top_level.txt
padatious_phoenix-0.4.9.0.dist-info/zip-safe
padatious_phoenix-0.4.9.0.dist-info/RECORD
