Metadata-Version: 2.1
Name: padatious-phoenix
Version: 0.4.9.0
Summary: A neural network intent parser
Home-page: http://github.com/MycroftPhoenix/padatious
Author: Matthew Scholefield
Author-email: matthew331199@gmail.com
Maintainer: Steve Chrétien
Maintainer-email: stevechretien111@protonmail.com
License: Apache-2.0
Keywords: intent-parser parser text text-processing
Classifier: Development Status :: 3 - Alpha
Classifier: Intended Audience :: Developers
Classifier: Topic :: Text Processing :: Linguistic
Classifier: License :: OSI Approved :: Apache Software License
Classifier: Programming Language :: Python :: 3.6
Classifier: Programming Language :: Python :: 3.7
Classifier: Programming Language :: Python :: 3.8
License-File: LICENSE
Requires-Dist: scikit-learn ==1.2.2
Requires-Dist: xxhash
Requires-Dist: padaos
Requires-Dist: NumPy ==1.17.3
Requires-Dist: scipy ==1.6.0
Requires-Dist: joblib ==1.1.1
Requires-Dist: threadpoolctl >=2.0.0
